Metadata-Version: 1.0
Name: pydetect
Version: 0.2.0
Summary: Change point and anomaly detector for time-series
Home-page: http://pydetect.readthedocs.org/en/stable
Author: sinhrks
Author-email: sinhrks@gmail.com
License: BSD
Platform: UNKNOWN
